pdfbox/__init__.py
python_pdfbox-0.1.8.1.dist-info/AUTHORS.rst
python_pdfbox-0.1.8.1.dist-info/LICENSE.rst
python_pdfbox-0.1.8.1.dist-info/METADATA
python_pdfbox-0.1.8.1.dist-info/WHEEL
python_pdfbox-0.1.8.1.dist-info/top_level.txt
python_pdfbox-0.1.8.1.dist-info/RECORD
