Metadata-Version: 2.1
Name: python-pdfbox
Version: 0.1.8.1
Summary: Python interface to Apache PDFBox command-line tools.
Home-page: https://github.com/lebedov/python-pdfbox/
Author: Lev E. Givon
Author-email: lev@columbia.edu
License: Apache
Platform: UNKNOWN
Classifier: Development Status :: 3 - Alpha
Classifier: Environment :: Console
Classifier: Intended Audience :: Developers
Classifier: License :: OSI Approved :: Apache Software License
Classifier: Operating System :: OS Independent
Classifier: Programming Language :: Python :: 3
Classifier: Topic :: Software Development
Requires-Python: >=3
Requires-Dist: appdirs
Requires-Dist: jpype1
Requires-Dist: setuptools
